annosSQL/Donos/__init__.py
annosSQL/Donos/docache.py
annosSQL/Donos/doconn.py
annosSQL/Donos/dosql.py
annosSQL/Innos/Interface.py
annosSQL/Innos/__init__.py
annosSQL/test/__init__.py
annosSQL/test/t3.py
annosSQL/test/t4.py
annosSQL/test/tesys.py
annosSQL-2.0.0.dist-info/METADATA
annosSQL-2.0.0.dist-info/RECORD
annosSQL-2.0.0.dist-info/WHEEL
annosSQL-2.0.0.dist-info/top_level.txt
