Metadata-Version: 2.1
Name: annosSQL
Version: 2.0.0
Summary: python for mysql operation
Home-page: https://gitee.com/chx516/annosSQL
Author: czh
Author-email: utowe@qq.com
License: MIT
Keywords: python annos
Platform: UNKNOWN
Requires-Python: >=3
Requires-Dist: pymysql
